pydzn/__init__.py
pydzn/base_component.py
pydzn/dzn.py
pydzn/grid_builder.py
pydzn/htmx.py
pydzn/responsive.py
pydzn/variants.py
pydzn/components/__init__.py
pydzn/components/button/__init__.py
pydzn/components/button/component.py
pydzn/components/button/template.html
pydzn/components/card/component.py
pydzn/components/card/template.html
pydzn/components/drawer/component.py
pydzn/components/drawer/template.html
pydzn/components/form/component.py
pydzn/components/form/template.html
pydzn/components/hamburger_menu/component.py
pydzn/components/hamburger_menu/template.html
pydzn/components/iframe/component.py
pydzn/components/iframe/template.html
pydzn/components/image/component.py
pydzn/components/image/template.html
pydzn/components/labeled_input/component.py
pydzn/components/labeled_input/template.html
pydzn/components/labeled_textarea/component.py
pydzn/components/labeled_textarea/template.html
pydzn/components/nav_item/component.py
pydzn/components/nav_item/template.html
pydzn/components/sidebar/component.py
pydzn/components/sidebar/template.html
pydzn/components/table/__init__.py
pydzn/components/table/component.py
pydzn/components/table/template.html
pydzn/components/text/component.py
pydzn/components/text/template.html
pydzn-0.1.9.dist-info/licenses/LICENSE
pydzn-0.1.9.dist-info/METADATA
pydzn-0.1.9.dist-info/WHEEL
pydzn-0.1.9.dist-info/top_level.txt
pydzn-0.1.9.dist-info/RECORD
